PyIAC/__init__.py
PyIAC/_singleton.py
PyIAC/buffer.py
PyIAC/context.py
PyIAC/core.py
PyIAC/models.py
PyIAC/state_machine.py
PyIAC/status_codes.py
PyIAC/alarms/__init__.py
PyIAC/alarms/alarms.py
PyIAC/alarms/states.py
PyIAC/alarms/trigger.py
PyIAC/dbmodels/__init__.py
PyIAC/dbmodels/alarms.py
PyIAC/dbmodels/core.py
PyIAC/dbmodels/tags.py
PyIAC/examples/__init__.py
PyIAC/examples/alarm_management_system.py
PyIAC/examples/data_acquisition_system.py
PyIAC/logger/__init__.py
PyIAC/logger/datalogger.py
PyIAC/logger/engine.py
PyIAC/logger/logdict.py
PyIAC/logger/query.py
PyIAC/managers/__init__.py
PyIAC/managers/alarms.py
PyIAC/managers/logger.py
PyIAC/managers/state_machine.py
PyIAC/src/__init__.py
PyIAC/src/units.json
PyIAC/src/variables.json
PyIAC/tags/__init__.py
PyIAC/tags/cvt.py
PyIAC/tags/tag.py
PyIAC/tags/tag_binding.py
PyIAC/tags/tag_value.py
PyIAC/tags/unit_conversion.py
PyIAC/tests/__init__.py
PyIAC/tests/test_alarm_manager.py
PyIAC/tests/test_alarm_states.py
PyIAC/tests/test_bool_alarms.py
PyIAC/tests/test_dbmodels.py
PyIAC/tests/test_dbmodels_from_config_file.py
PyIAC/tests/test_high_alarms.py
PyIAC/tests/test_high_high_alarms.py
PyIAC/tests/test_low_alarms.py
PyIAC/tests/test_low_low_alarms.py
PyIAC/tests/test_unit_conversion.py
PyIAC/tests/test_unit_conversion_from_tags.py
PyIAC/utils/__init__.py
PyIAC/utils/_errors.py
PyIAC/utils/inspect.py
PyIAC/utils/observer.py
PyIAC/utils/others.py
PyIAC/workers/__init__.py
PyIAC/workers/alarms.py
PyIAC/workers/continuos.py
PyIAC/workers/logger.py
PyIAC/workers/state_machine.py
PyIAC/workers/worker.py
PyIAC-1.0.0.dist-info/LICENSE
PyIAC-1.0.0.dist-info/METADATA
PyIAC-1.0.0.dist-info/WHEEL
PyIAC-1.0.0.dist-info/top_level.txt
PyIAC-1.0.0.dist-info/RECORD
