Metadata-Version: 2.1
Name: PyIAC
Version: 1.0.0
Summary: A python library to develop automation continuous tasks using sync or async concurrent threads
Home-page: https://github.com/know-ai/PyIAC
Author: KnowAI
Author-email: dev.know.ai@gmail.com
License: GNU AFFERO GENERAL PUBLIC LICENSE
Platform: UNKNOWN
Classifier: Programming Language :: Python :: 3.7
Classifier: Programming Language :: Python :: 3.8
Classifier: Programming Language :: Python :: 3.9
Classifier: Programming Language :: Python :: 3.10
Classifier: Programming Language :: Python :: 3.11
Classifier: License :: OSI Approved :: GNU Affero General Public License v3
Classifier: Operating System :: OS Independent
Classifier: Topic :: Software Development :: Libraries
Classifier: Topic :: System :: Logging
Classifier: Topic :: System :: Monitoring
License-File: LICENSE
Requires-Dist: PyYAML ==6.0
Requires-Dist: peewee ==3.15.4
Requires-Dist: python-dotenv ==0.21.1
Requires-Dist: python-socketio ==5.8.0
Requires-Dist: python-statemachine ==0.8.0
Requires-Dist: requests ==2.28.2
Requires-Dist: tqdm >=4.50.2
Requires-Dist: psycopg2-binary ==2.9.5 ; sys_platform != "win32"
Requires-Dist: psycopg2 ==2.9.5 ; sys_platform == "win32"
